{"nm":"Main Scene","ddd":0,"h":150,"w":190,"meta":{"g":"@lottiefiles/creator 1.42.2"},"layers":[{"ty":4,"nm":"BILL","sr":1,"st":0,"op":181.000007372281,"ip":0,"hd":false,"ddd":0,"bm":0,"hasMask":false,"ao":0,"ks":{"a":{"a":0,"k":[473.5,285,0],"ix":1},"s":{"a":0,"k":[10.8,10.8,100],"ix":6},"sk":{"a":0,"k":0},"p":{"a":1,"k":[{"o":{"x":1,"y":0},"i":{"x":0.833,"y":1},"s":[95,-30,0],"t":0},{"o":{"x":0.167,"y":0.167},"i":{"x":0.833,"y":0.833},"s":[95,116.7,0],"t":19},{"o":{"x":1,"y":0},"i":{"x":0.833,"y":0.833},"s":[95,116.7,0],"t":57},{"s":[95,184.7,0],"t":72.0000029326201}],"ix":2},"r":{"a":0,"k":0,"ix":10},"sa":{"a":0,"k":0},"o":{"a":0,"k":100,"ix":11}},"shapes":[{"ty":"gr","bm":0,"hd":false,"mn":"ADBE Vector Group","nm":"Group 2","ix":2,"cix":2,"np":6,"it":[{"ty":"sh","bm":0,"hd":false,"mn":"ADBE Vector Shape - Group","nm":"Path 1","ix":1,"d":1,"ks":{"a":0,"k":{"c":true,"i":[[8.756,-5.054],[10.112,5.838],[-8.758,5.054],[-10.111,-5.838]],"o":[[-8.757,5.057],[-10.111,-5.837],[8.757,-5.057],[10.112,5.838]],"v":[[-157.923,103.83],[-192.087,102.414],[-194.539,82.691],[-160.376,84.106]]},"ix":2}},{"ty":"sh","bm":0,"hd":false,"mn":"ADBE Vector Shape - Group","nm":"Path 2","ix":2,"d":1,"ks":{"a":0,"k":{"c":true,"i":[[8.757,-5.055],[10.111,5.838],[-8.755,5.054],[-10.112,-5.837]],"o":[[-8.757,5.056],[-10.113,-5.84],[8.757,-5.057],[10.111,5.838]],"v":[[180.697,-91.265],[146.534,-92.681],[144.08,-112.405],[178.245,-110.99]]},"ix":2}},{"ty":"sh","bm":0,"hd":false,"mn":"ADBE Vector Shape - Group","nm":"Path 3","ix":3,"d":1,"ks":{"a":0,"k":{"c":true,"i":[[0,0],[0.955,0.551],[15.308,-7.889],[0,0],[17.262,9.966],[0.904,0.454],[0,0],[-0.907,-0.524],[-15.303,7.904],[0,0],[-17.015,-9.824],[-1.049,-0.516]],"o":[[-0.862,-0.58],[-16.929,-9.775],[0,0],[14.576,-8.772],[-0.863,-0.498],[0,0],[0.822,0.55],[16.939,9.78],[0,0],[-13.897,8.821],[0.995,0.574],[0,0]],"v":[[-126.144,181.9],[-128.86,180.199],[-186.442,176.99],[-306.481,107.834],[-311.202,74.078],[-313.86,72.656],[126.729,-182.262],[129.313,-180.648],[186.921,-177.453],[307.234,-107.99],[312.578,-74.615],[315.65,-72.983]]},"ix":2}},{"ty":"sh","bm":0,"hd":false,"mn":"ADBE Vector Shape - Group","nm":"Path 4","ix":4,"d":1,"ks":{"a":0,"k":{"c":true,"i":[[0,0],[0.174,0.1],[0.182,0.102],[0,0],[0,0],[0.046,-0.027],[0.047,-0.027],[0,0],[0,0],[0,0]],"o":[[-0.17,-0.102],[-0.18,-0.104],[0,0],[0,0],[-0.048,0.027],[-0.047,0.027],[0,0],[0,0],[0,0],[0,0]],"v":[[184.57,-211.953],[184.064,-212.259],[183.515,-212.562],[152.43,-230.494],[125.223,-214.782],[125.079,-214.704],[124.942,-214.62],[-399.355,88.153],[-152.333,230.494],[399.355,-88.051]]},"ix":2}},{"ty":"mm","bm":0,"hd":false,"mn":"ADBE Vector Filter - Merge","nm":"Merge Paths 1","mm":1},{"ty":"fl","bm":0,"hd":false,"mn":"ADBE Vector Graphic - Fill","nm":"Fill 1","c":{"a":0,"k":[0.1922,0.1922,0.5098],"ix":4},"r":1,"o":{"a":0,"k":100,"ix":5}},{"ty":"tr","a":{"a":0,"k":[-1.1368683772161603e-13,-2.2737367544323206e-13],"ix":1},"s":{"a":0,"k":[100,100],"ix":3},"sk":{"a":0,"k":0,"ix":4},"p":{"a":0,"k":[473.2439999999999,278.8719999999998],"ix":2},"r":{"a":0,"k":0,"ix":6},"sa":{"a":0,"k":0,"ix":5},"o":{"a":0,"k":100,"ix":7}}]},{"ty":"gr","bm":0,"hd":false,"mn":"ADBE Vector Group","nm":"Group 3","ix":3,"cix":2,"np":2,"it":[{"ty":"sh","bm":0,"hd":false,"mn":"ADBE Vector Shape - Group","nm":"Path 1","ix":1,"d":1,"ks":{"a":0,"k":{"c":true,"i":[[0,0],[0,0],[0,0],[0,0]],"o":[[0,0],[0,0],[0,0],[0,0]],"v":[[341.207,-87.838],[152.07,-197.037],[-341.207,88.366],[-152.574,197.037]]},"ix":2}},{"ty":"fl","bm":0,"hd":false,"mn":"ADBE Vector Graphic - Fill","nm":"Fill 1","c":{"a":0,"k":[0.9569,0.9569,0.9569],"ix":4},"r":1,"o":{"a":0,"k":100,"ix":5}},{"ty":"tr","a":{"a":0,"k":[0,0],"ix":1},"s":{"a":0,"k":[100,100],"ix":3},"sk":{"a":0,"k":0,"ix":4},"p":{"a":0,"k":[473.806,278.659],"ix":2},"r":{"a":0,"k":0,"ix":6},"sa":{"a":0,"k":0,"ix":5},"o":{"a":0,"k":100,"ix":7}}]},{"ty":"gr","bm":0,"hd":false,"mn":"ADBE Vector Group","nm":"Group 4","ix":4,"cix":2,"np":2,"it":[{"ty":"sh","bm":0,"hd":false,"mn":"ADBE Vector Shape - Group","nm":"Path 1","ix":1,"d":1,"ks":{"a":0,"k":{"c":true,"i":[[0,0],[0,0],[0,0],[0,0],[0,0]],"o":[[0,0],[0,0],[0,0],[0,0],[0,0]],"v":[[-345.844,152.548],[-457.585,87.958],[152.527,-264.291],[457.585,-88.166],[-152.528,264.291]]},"ix":2}},{"ty":"fl","bm":0,"hd":false,"mn":"ADBE Vector Graphic - Fill","nm":"Fill 1","c":{"a":0,"k":[0.8588,0.8588,0.8588],"ix":4},"r":1,"o":{"a":0,"k":100,"ix":5}},{"ty":"tr","a":{"a":0,"k":[-1.1368683772161603e-13,0],"ix":1},"s":{"a":0,"k":[100,100],"ix":3},"sk":{"a":0,"k":0,"ix":4},"p":{"a":0,"k":[473.1129999999999,278.987],"ix":2},"r":{"a":0,"k":0,"ix":6},"sa":{"a":0,"k":0,"ix":5},"o":{"a":0,"k":100,"ix":7}}]},{"ty":"gr","bm":0,"hd":false,"mn":"ADBE Vector Group","nm":"Group 5","ix":5,"cix":2,"np":2,"it":[{"ty":"sh","bm":0,"hd":false,"mn":"ADBE Vector Shape - Group","nm":"Path 1","ix":1,"d":1,"ks":{"a":0,"k":{"c":true,"i":[[0,0],[0,0],[0,0],[0,0]],"o":[[0,0],[0,0],[0,0],[0,0]],"v":[[305.057,-182.499],[305.057,-168.93],[-305.056,182.499],[-305.056,169.958]]},"ix":2}},{"ty":"fl","bm":0,"hd":false,"mn":"ADBE Vector Graphic - Fill","nm":"Fill 1","c":{"a":0,"k":[0.7686,0.7686,0.7686],"ix":4},"r":1,"o":{"a":0,"k":100,"ix":5}},{"ty":"tr","a":{"a":0,"k":[0.0005035400388351263,0],"ix":1},"s":{"a":0,"k":[100,100],"ix":3},"sk":{"a":0,"k":0,"ix":4},"p":{"a":0,"k":[625.6415035400388,373.32],"ix":2},"r":{"a":0,"k":0,"ix":6},"sa":{"a":0,"k":0,"ix":5},"o":{"a":0,"k":100,"ix":7}}]},{"ty":"gr","bm":0,"hd":false,"mn":"ADBE Vector Group","nm":"Group 6","ix":6,"cix":2,"np":2,"it":[{"ty":"sh","bm":0,"hd":false,"mn":"ADBE Vector Shape - Group","nm":"Path 1","ix":1,"d":1,"ks":{"a":0,"k":{"c":true,"i":[[0,0],[0,0],[0,0],[0,0],[0,0],[0,0]],"o":[[0,0],[0,0],[0,0],[0,0],[0,0],[0,0]],"v":[[457.585,-94.436],[457.585,-80.867],[-152.528,270.562],[-457.585,94.649],[-457.585,81.688],[152.527,-270.562]]},"ix":2}},{"ty":"fl","bm":0,"hd":false,"mn":"ADBE Vector Graphic - Fill","nm":"Fill 1","c":{"a":0,"k":[0.6667,0.6667,0.6667],"ix":4},"r":1,"o":{"a":0,"k":100,"ix":5}},{"ty":"tr","a":{"a":0,"k":[-1.1368683772161603e-13,-2.2737367544323206e-13],"ix":1},"s":{"a":0,"k":[100,100],"ix":3},"sk":{"a":0,"k":0,"ix":4},"p":{"a":0,"k":[473.1129999999999,285.2569999999998],"ix":2},"r":{"a":0,"k":0,"ix":6},"sa":{"a":0,"k":0,"ix":5},"o":{"a":0,"k":100,"ix":7}}]}],"ind":1},{"ty":4,"nm":"Shape Layer 4","sr":1,"st":2.00000008146167,"op":34.0000013848484,"ip":22.0000008960784,"hd":false,"ddd":0,"bm":0,"hasMask":false,"ao":0,"ks":{"a":{"a":0,"k":[0.5000000000000036,-67.50000000000001],"ix":1},"s":{"a":0,"k":[100,100,100],"ix":6},"sk":{"a":0,"k":0},"p":{"a":0,"k":[32.625000000000014,24.34730547410682],"ix":2},"r":{"a":0,"k":-30,"ix":10},"sa":{"a":0,"k":0},"o":{"a":0,"k":100,"ix":11}},"shapes":[{"ty":"gr","bm":0,"hd":false,"mn":"ADBE Vector Group","nm":"Shape 1","ix":1,"cix":2,"np":2,"it":[{"ty":"sh","bm":0,"hd":false,"mn":"ADBE Vector Shape - Group","nm":"Path 1","ix":1,"d":1,"ks":{"a":1,"k":[{"o":{"x":0.167,"y":0.167},"i":{"x":0.833,"y":0.833},"s":[{"c":false,"i":[[0,0],[0,0]],"o":[[0,0],[0,0]],"v":[[0.5,3.75],[0.5,8.75]]}],"t":22},{"o":{"x":0.167,"y":0.167},"i":{"x":0.196,"y":1},"s":[{"c":false,"i":[[0,0],[0,0]],"o":[[0,0],[0,0]],"v":[[0.5,-17.75],[0.5,8.75]]}],"t":26},{"s":[{"c":false,"i":[[0,0],[0,0]],"o":[[0,0],[0,0]],"v":[[0.5,-17.75],[0.5,-17.5]]}],"t":34.0000013848484}],"ix":2}},{"ty":"st","bm":0,"hd":false,"mn":"ADBE Vector Graphic - Stroke","nm":"Stroke 2","lc":2,"lj":1,"ml":4,"o":{"a":0,"k":100,"ix":4},"w":{"a":0,"k":6,"ix":5},"c":{"a":0,"k":[1,0.5686,0],"ix":3}},{"ty":"tr","a":{"a":0,"k":[0,0],"ix":1},"s":{"a":0,"k":[100,100],"ix":3},"sk":{"a":0,"k":0,"ix":4},"p":{"a":1,"k":[{"o":{"x":0.167,"y":0.167},"i":{"x":0.833,"y":0.833},"s":[0,40],"t":22},{"o":{"x":0.167,"y":0.167},"i":{"x":0.196,"y":1},"s":[0,-12],"t":26},{"s":[0,-50],"t":34.0000013848484}],"ix":2},"r":{"a":0,"k":0,"ix":6},"sa":{"a":0,"k":0,"ix":5},"o":{"a":0,"k":100,"ix":7}}]}],"ind":2},{"ty":4,"nm":"Shape Layer 3","sr":1,"st":1.00000004073083,"op":34.0000013848484,"ip":21.0000008553475,"hd":false,"ddd":0,"bm":0,"hasMask":false,"ao":0,"ks":{"a":{"a":0,"k":[0.5,-67.5],"ix":1},"s":{"a":0,"k":[100,100,100],"ix":6},"sk":{"a":0,"k":0},"p":{"a":0,"k":[62.95350507835802,11.784827344149662],"ix":2},"r":{"a":0,"k":-15,"ix":10},"sa":{"a":0,"k":0},"o":{"a":0,"k":100,"ix":11}},"shapes":[{"ty":"gr","bm":0,"hd":false,"mn":"ADBE Vector Group","nm":"Shape 1","ix":1,"cix":2,"np":2,"it":[{"ty":"sh","bm":0,"hd":false,"mn":"ADBE Vector Shape - Group","nm":"Path 1","ix":1,"d":1,"ks":{"a":1,"k":[{"o":{"x":0.167,"y":0.167},"i":{"x":0.833,"y":0.833},"s":[{"c":false,"i":[[0,0],[0,0]],"o":[[0,0],[0,0]],"v":[[0.5,3.75],[0.5,8.75]]}],"t":21},{"o":{"x":0.167,"y":0.167},"i":{"x":0.196,"y":1},"s":[{"c":false,"i":[[0,0],[0,0]],"o":[[0,0],[0,0]],"v":[[0.5,-17.75],[0.5,8.75]]}],"t":25},{"s":[{"c":false,"i":[[0,0],[0,0]],"o":[[0,0],[0,0]],"v":[[0.5,-17.75],[0.5,-17.5]]}],"t":34.0000013848484}],"ix":2}},{"ty":"st","bm":0,"hd":false,"mn":"ADBE Vector Graphic - Stroke","nm":"Stroke 2","lc":2,"lj":1,"ml":4,"o":{"a":0,"k":100,"ix":4},"w":{"a":0,"k":6,"ix":5},"c":{"a":0,"k":[1,0.5686,0],"ix":3}},{"ty":"tr","a":{"a":0,"k":[0,0],"ix":1},"s":{"a":0,"k":[100,100],"ix":3},"sk":{"a":0,"k":0,"ix":4},"p":{"a":1,"k":[{"o":{"x":0.167,"y":0.167},"i":{"x":0.833,"y":0.833},"s":[0,40],"t":21},{"o":{"x":0.167,"y":0.167},"i":{"x":0.196,"y":1},"s":[0,-12],"t":25},{"s":[0,-50],"t":34.0000013848484}],"ix":2},"r":{"a":0,"k":0,"ix":6},"sa":{"a":0,"k":0,"ix":5},"o":{"a":0,"k":100,"ix":7}}]}],"ind":3},{"ty":4,"nm":"Shape Layer 5","sr":1,"st":2.00000008146167,"op":34.0000013848484,"ip":22.0000008960784,"hd":false,"ddd":0,"bm":0,"hasMask":false,"ao":0,"ks":{"a":{"a":0,"k":[0.5,58.25,0],"ix":1},"s":{"a":0,"k":[100,100,100],"ix":6},"sk":{"a":0,"k":0},"p":{"a":0,"k":[95.5,133.25,0],"ix":2},"r":{"a":0,"k":30,"ix":10},"sa":{"a":0,"k":0},"o":{"a":0,"k":100,"ix":11}},"shapes":[{"ty":"gr","bm":0,"hd":false,"mn":"ADBE Vector Group","nm":"Shape 1","ix":1,"cix":2,"np":2,"it":[{"ty":"sh","bm":0,"hd":false,"mn":"ADBE Vector Shape - Group","nm":"Path 1","ix":1,"d":1,"ks":{"a":1,"k":[{"o":{"x":0.167,"y":0.167},"i":{"x":0.833,"y":0.833},"s":[{"c":false,"i":[[0,0],[0,0]],"o":[[0,0],[0,0]],"v":[[0.5,3.75],[0.5,8.75]]}],"t":22},{"o":{"x":0.167,"y":0.167},"i":{"x":0.196,"y":1},"s":[{"c":false,"i":[[0,0],[0,0]],"o":[[0,0],[0,0]],"v":[[0.5,-17.75],[0.5,8.75]]}],"t":26},{"s":[{"c":false,"i":[[0,0],[0,0]],"o":[[0,0],[0,0]],"v":[[0.5,-17.75],[0.5,-17.5]]}],"t":34.0000013848484}],"ix":2}},{"ty":"st","bm":0,"hd":false,"mn":"ADBE Vector Graphic - Stroke","nm":"Stroke 2","lc":2,"lj":1,"ml":4,"o":{"a":0,"k":100,"ix":4},"w":{"a":0,"k":6,"ix":5},"c":{"a":0,"k":[1,0.5686,0],"ix":3}},{"ty":"tr","a":{"a":0,"k":[0,0],"ix":1},"s":{"a":0,"k":[100,100],"ix":3},"sk":{"a":0,"k":0,"ix":4},"p":{"a":1,"k":[{"o":{"x":0.167,"y":0.167},"i":{"x":0.833,"y":0.833},"s":[0,40],"t":22},{"o":{"x":0.167,"y":0.167},"i":{"x":0.196,"y":1},"s":[0,-12],"t":26},{"s":[0,-50],"t":34.0000013848484}],"ix":2},"r":{"a":0,"k":0,"ix":6},"sa":{"a":0,"k":0,"ix":5},"o":{"a":0,"k":100,"ix":7}}]}],"ind":4},{"ty":4,"nm":"Shape Layer 2","sr":1,"st":1.00000004073083,"op":34.0000013848484,"ip":21.0000008553475,"hd":false,"ddd":0,"bm":0,"hasMask":false,"ao":0,"ks":{"a":{"a":0,"k":[0.5,58.25,0],"ix":1},"s":{"a":0,"k":[100,100,100],"ix":6},"sk":{"a":0,"k":0},"p":{"a":0,"k":[95.5,133.25,0],"ix":2},"r":{"a":0,"k":15,"ix":10},"sa":{"a":0,"k":0},"o":{"a":0,"k":100,"ix":11}},"shapes":[{"ty":"gr","bm":0,"hd":false,"mn":"ADBE Vector Group","nm":"Shape 1","ix":1,"cix":2,"np":2,"it":[{"ty":"sh","bm":0,"hd":false,"mn":"ADBE Vector Shape - Group","nm":"Path 1","ix":1,"d":1,"ks":{"a":1,"k":[{"o":{"x":0.167,"y":0.167},"i":{"x":0.833,"y":0.833},"s":[{"c":false,"i":[[0,0],[0,0]],"o":[[0,0],[0,0]],"v":[[0.5,3.75],[0.5,8.75]]}],"t":21},{"o":{"x":0.167,"y":0.167},"i":{"x":0.196,"y":1},"s":[{"c":false,"i":[[0,0],[0,0]],"o":[[0,0],[0,0]],"v":[[0.5,-17.75],[0.5,8.75]]}],"t":25},{"s":[{"c":false,"i":[[0,0],[0,0]],"o":[[0,0],[0,0]],"v":[[0.5,-17.75],[0.5,-17.5]]}],"t":34.0000013848484}],"ix":2}},{"ty":"st","bm":0,"hd":false,"mn":"ADBE Vector Graphic - Stroke","nm":"Stroke 2","lc":2,"lj":1,"ml":4,"o":{"a":0,"k":100,"ix":4},"w":{"a":0,"k":6,"ix":5},"c":{"a":0,"k":[1,0.5686,0],"ix":3}},{"ty":"tr","a":{"a":0,"k":[0,0],"ix":1},"s":{"a":0,"k":[100,100],"ix":3},"sk":{"a":0,"k":0,"ix":4},"p":{"a":1,"k":[{"o":{"x":0.167,"y":0.167},"i":{"x":0.833,"y":0.833},"s":[0,40],"t":21},{"o":{"x":0.167,"y":0.167},"i":{"x":0.196,"y":1},"s":[0,-12],"t":25},{"s":[0,-50],"t":34.0000013848484}],"ix":2},"r":{"a":0,"k":0,"ix":6},"sa":{"a":0,"k":0,"ix":5},"o":{"a":0,"k":100,"ix":7}}]}],"ind":5},{"ty":4,"nm":"Shape Layer 1","sr":1,"st":0,"op":34.0000013848484,"ip":20.0000008146167,"hd":false,"ddd":0,"bm":0,"hasMask":false,"ao":0,"ks":{"a":{"a":0,"k":[0.5,58.25,0],"ix":1},"s":{"a":0,"k":[100,100,100],"ix":6},"sk":{"a":0,"k":0},"p":{"a":0,"k":[95.5,133.25,0],"ix":2},"r":{"a":0,"k":0,"ix":10},"sa":{"a":0,"k":0},"o":{"a":0,"k":100,"ix":11}},"shapes":[{"ty":"gr","bm":0,"hd":false,"mn":"ADBE Vector Group","nm":"Shape 1","ix":1,"cix":2,"np":2,"it":[{"ty":"sh","bm":0,"hd":false,"mn":"ADBE Vector Shape - Group","nm":"Path 1","ix":1,"d":1,"ks":{"a":1,"k":[{"o":{"x":0.167,"y":0.167},"i":{"x":0.833,"y":0.833},"s":[{"c":false,"i":[[0,0],[0,0]],"o":[[0,0],[0,0]],"v":[[0.5,3.75],[0.5,8.75]]}],"t":20},{"o":{"x":0.167,"y":0.167},"i":{"x":0.196,"y":1},"s":[{"c":false,"i":[[0,0],[0,0]],"o":[[0,0],[0,0]],"v":[[0.5,-17.75],[0.5,8.75]]}],"t":24},{"s":[{"c":false,"i":[[0,0],[0,0]],"o":[[0,0],[0,0]],"v":[[0.5,-17.75],[0.5,-17.5]]}],"t":34.0000013848484}],"ix":2}},{"ty":"st","bm":0,"hd":false,"mn":"ADBE Vector Graphic - Stroke","nm":"Stroke 2","lc":2,"lj":1,"ml":4,"o":{"a":0,"k":100,"ix":4},"w":{"a":0,"k":6,"ix":5},"c":{"a":0,"k":[1,0.5686,0],"ix":3}},{"ty":"tr","a":{"a":0,"k":[0,0],"ix":1},"s":{"a":0,"k":[100,100],"ix":3},"sk":{"a":0,"k":0,"ix":4},"p":{"a":1,"k":[{"o":{"x":0.167,"y":0.167},"i":{"x":0.833,"y":0.833},"s":[0,40],"t":20},{"o":{"x":0.167,"y":0.167},"i":{"x":0.196,"y":1},"s":[0,-12],"t":24},{"s":[0,-50],"t":34.0000013848484}],"ix":2},"r":{"a":0,"k":0,"ix":6},"sa":{"a":0,"k":0,"ix":5},"o":{"a":0,"k":100,"ix":7}}]}],"ind":6}],"v":"5.7.0","fr":29.9700012207031,"op":84,"ip":0,"assets":[],"markers":[{"cm":"1","tm":0,"dr":0}]}